{
  "investments": [
    {
      "id": 1,
      "description": "Meta de renda passiva",
      "icon": "money-bill",
      "toAport": 3,
      "fromDate": "2023-8-24 1:51:29",
      "title": "Nubank RDB",
      "subtitle": "FIE",
      "profitPercentage": 12,
      "profitCalendarType": "months",
      "fromBudget": 53897.32,
      "toBudget": 100000
    }
  ],
  "investwallet": [
    {
      "investmentbalance": {
        "value": 54001.25,
        "percentage": 10
      },
      "accountbalance": {
        "value": 282.59,
        "percentage": 30
      },
      "passiveincoming": {
        "value": 23.95,
        "percentage": 12
      }
    }
  ],
  "creditcard": {
    "current_statement": 2990.8
  },
  "banking": {
    "account_balance": 2773.36,
    "current_incoming": 7741,
    "current_expenses": 4967.639999999999
  }
}